CHANGELOG.txt
LICENCE.txt
MANIFEST.in
README.txt
setup.py
snapalgo/__init__.py
snapalgo.egg-info/PKG-INFO
snapalgo.egg-info/SOURCES.txt
snapalgo.egg-info/dependency_links.txt
snapalgo.egg-info/requires.txt
snapalgo.egg-info/top_level.txt
snapalgo/sorting/__init__.py
snapalgo/template_generator/__init__.py
snapalgo/template_generator/segment_tree.py
snapalgo/template_generator/trie.py
snapalgo/template_generator/union_find.py
snapalgo/trees/__init__.py