Metadata-Version: 2.1
Name: snapalgo
Version: 0.0.6.7
Summary: Various Coding algorithms
Home-page: https://github.com/midnightbot/snapalgo
Author: Anish Adnani
Author-email: anishadnani00@gmail.com
License: MIT
Keywords: python,coding,template,algo,algorithms
Platform: UNKNOWN
Classifier: Development Status :: 5 - Production/Stable
Classifier: Intended Audience :: Developers
Classifier: Programming Language :: Python :: 3
Classifier: Operating System :: Unix
Classifier: Operating System :: MacOS :: MacOS X
Classifier: Operating System :: Microsoft :: Windows
License-File: LICENCE.txt
